{"kind":"RuntimeSemantics","params":["this","BindingPropertyList","BindingRestProperty","value","environment"],"steps":[{"tokens":["Let",{"id":"excludedNames"},"be","?","PropertyBindingInitialization","of",{"nt":"BindingPropertyList"},"with","arguments",{"id":"value"},"and",{"id":"environment"},"."]},{"tokens":["Return","the","result","of","performing","RestBindingInitialization","of",{"nt":"BindingRestProperty"},"with","arguments",{"id":"value"},",",{"id":"environment"},",","and",{"id":"excludedNames"},"."]}],"length":0,"filename":"es2020_prop/algorithm/ObjectBindingPattern3BindingInitialization1.json"}