{"kind":"StaticSemantics","lang":true,"params":["this","NoSubstitutionTemplate","raw"],"steps":[{"tokens":["If",{"id":"raw"},"is",{"value":"false"},",","then",{"steps":[{"tokens":["Let",{"id":"string"},"be","the","TV","of",{"nt":"NoSubstitutionTemplate"},"."]}]}]},{"tokens":["Else",",",{"steps":[{"tokens":["Let",{"id":"string"},"be","the","TRV","of",{"nt":"NoSubstitutionTemplate"},"."]}]}]},{"tokens":["Return","a","List","containing","the","single","element",",",{"id":"string"},"."]}],"length":0,"filename":"es2020/algorithm/TemplateLiteral0TemplateStrings0.json"}