{"kind":"RuntimeSemantics","params":["e"],"steps":[{"tokens":["If",{"id":"e"},"is","-","1","or",{"id":"e"},"is",{"id":"InputLength"},",","return",{"value":"false"},"."]},{"tokens":["Let",{"id":"c"},"be","the","character",{"id":"Input"},"[",{"id":"e"},"]","."]},{"tokens":["Let",{"id":"wordChars"},"be","the","result","of","!","WordCharacters","(",")","."]},{"tokens":["If",{"id":"c"},"is","in",{"id":"wordChars"},",","return",{"value":"true"},"."]},{"tokens":["Return",{"value":"false"},"."]}],"filename":"es2018/algorithm/IsWordChar.json"}