{"kind":"Method","lang":true,"params":["this","N","S"],"steps":[{"tokens":["Let",{"id":"envRec"},"be","the","declarative","Environment","Record","for","which","the","method","was","invoked","."]},{"tokens":["Assert",":",{"id":"envRec"},"has","a","binding","for",{"id":"N"},"."]},{"tokens":["If","the","binding","for",{"id":"N"},"in",{"id":"envRec"},"is","an","uninitialized","binding",",","throw","a",{"value":"ReferenceError"},"exception","."]},{"tokens":["Return","the","value","currently","bound","to",{"id":"N"},"in",{"id":"envRec"},"."]}],"length":2,"filename":"es2019/algorithm/DeclarativeEnvironmentRecord.GetBindingValue.json"}