{"kind":"Builtin","params":[],"steps":[{"tokens":["If","Type","(",{"id":"O"},")","is","not","Object",",","return",{"value":"false"},"."]},{"tokens":["Let",{"id":"spreadable"},"be","?","Get","(",{"id":"O"},",","@","@","isConcatSpreadable",")","."]},{"tokens":["If",{"id":"spreadable"},"is","not",{"value":"undefined"},",","return","ToBoolean","(",{"id":"spreadable"},")","."]},{"tokens":["Return","?","IsArray","(",{"id":"O"},")","."]}],"length":0,"filename":"es2000/algorithm/22.1.3.1.1RuntimeSemantics:IsConcatSpreadable(O)0.json"}