{"kind":"Language","params":[],"steps":[{"tokens":["ReturnIfAbrupt","(",{"id":"V"},")","."]},{"tokens":["If","Type","(",{"id":"V"},")","is","not","Reference",",","return",{"id":"V"},"."]},{"tokens":["Let",{"id":"base"},"be","GetBase","(",{"id":"V"},")","."]},{"tokens":["If","IsUnresolvableReference","(",{"id":"V"},")","is",{"value":"true"},",","throw","a",{"value":"ReferenceError"},"exception","."]},{"tokens":["If","IsPropertyReference","(",{"id":"V"},")","is",{"value":"true"},",","then",{"steps":[{"tokens":["If","HasPrimitiveBase","(",{"id":"V"},")","is",{"value":"true"},",","then",{"steps":[{"tokens":["Assert",":","In","this","case",",",{"id":"base"},"will","never","be",{"value":"undefined"},"or",{"value":"null"},"."]},{"tokens":["Set",{"id":"base"},"to","!","ToObject","(",{"id":"base"},")","."]}]}]},{"tokens":["Return","?",{"id":"base"},".","[","[","Get","]","]","(","GetReferencedName","(",{"id":"V"},")",",","GetThisValue","(",{"id":"V"},")",")","."]}]}]},{"tokens":["Else",{"id":"base"},"must","be","an","Environment","Record",",",{"steps":[{"tokens":["Return","?",{"id":"base"},".","GetBindingValue","(","GetReferencedName","(",{"id":"V"},")",",","IsStrictReference","(",{"id":"V"},")",")","(","see","8",".","1",".","1",")","."]}]}]}],"length":0,"filename":"es2000/algorithm/6.2.4.1GetValue(V)0.json"}