{"kind":"RuntimeSemantics","params":["this","PropertyName","AssignmentElement","value"],"steps":[{"tokens":["Let",{"id":"name"},"be","the","result","of","evaluating",{"nt":"PropertyName"},"."]},{"tokens":["ReturnIfAbrupt","(",{"id":"name"},")","."]},{"tokens":["Return","the","result","of","performing","KeyedDestructuringAssignmentEvaluation","of",{"nt":"AssignmentElement"},"with",{"id":"value"},"and",{"id":"name"},"as","the","arguments","."]}],"length":0,"filename":"es2000/algorithm/AssignmentProperty1DestructuringAssignmentEvaluation0.json"}