{"kind":"Method","params":["argument"],"steps":[{"tokens":["Let",{"id":"number"},"be","?","ToNumber","(",{"id":"argument"},")","."]},{"tokens":["If",{"id":"number"},"is",{"value":"NaN"},",","return",{"value":"+0"},"."]},{"tokens":["If",{"id":"number"},"is",{"value":"+0"},",",{"value":"-0"},",",{"value":"+∞"},",","or",{"value":"-∞"},",","return",{"id":"number"},"."]},{"tokens":["Return","the","number","value","that","is","the","same","sign","as",{"id":"number"},"and","whose","magnitude","is","floor","(","abs","(",{"id":"number"},")",")","."]}],"length":1,"filename":"es2000/algorithm/ToInteger.json"}