{"kind":"Builtin","params":[],"steps":[{"tokens":["Let",{"id":"byteLocation"},"be",{"id":"byteIndex"},"."]},{"tokens":["Let",{"id":"bytesRead"},"be","a","new","empty","List","."]},{"tokens":["For","each","element",{"id":"W"},"of",{"id":"Ws"},"in","List","order",",","do",{"steps":[{"tokens":["Assert",":",{"id":"W"},"has",{"id":"byteLocation"},"in","its","range","."]},{"tokens":["Let",{"id":"payloadIndex"},"be",{"id":"byteLocation"},"-",{"id":"W"},".","[","[","ByteIndex","]","]","."]},{"tokens":["If",{"id":"W"},"is","a","WriteSharedMemory","event",",","then",{"steps":[{"tokens":["Let",{"id":"byte"},"be",{"id":"W"},".","[","[","Payload","]","]","[",{"id":"payloadIndex"},"]","."]}]}]},{"tokens":["Else",",",{"steps":[{"tokens":["Assert",":",{"id":"W"},"is","a","ReadModifyWriteSharedMemory","event","."]},{"tokens":["Let",{"id":"bytes"},"be","ValueOfReadEvent","(",{"id":"execution"},",",{"id":"W"},")","."]},{"tokens":["Let",{"id":"bytesModified"},"be",{"id":"W"},".","[","[","ModifyOp","]","]","(",{"id":"bytes"},",",{"id":"W"},".","[","[","Payload","]","]",")","."]},{"tokens":["Let",{"id":"byte"},"be",{"id":"bytesModified"},"[",{"id":"payloadIndex"},"]","."]}]}]},{"tokens":["Append",{"id":"byte"},"to",{"id":"bytesRead"},"."]},{"tokens":["Increment",{"id":"byteLocation"},"by","1","."]}]}]},{"tokens":["Return",{"id":"bytesRead"},"."]}],"length":0,"filename":"es2000/algorithm/27.5.4ComposeWriteEventBytes(execution,byteIndex,Ws)0.json"}